vesdk/__init__.py
vesdk/api/__init__.py
vesdk/api/image_generation.py
vesdk/api/knowledge.py
vesdk/api/memory.py
vesdk/api/text_generation.py
vesdk/api/video_generation.py
vesdk/core/__init__.py
vesdk/core/auth.py
vesdk/core/client.py
vesdk/core/exceptions.py
vesdk/tests/__init__.py
vesdk/tests/test_image_generation.py
vesdk/tests/test_knowledge.py
vesdk/tests/test_memory.py
vesdk/tests/test_text_generation.py
vesdk/tests/test_video_generation.py
vesdk-1.0.1.dist-info/licenses/LICENSE.txt
vesdk-1.0.1.dist-info/METADATA
vesdk-1.0.1.dist-info/WHEEL
vesdk-1.0.1.dist-info/top_level.txt
vesdk-1.0.1.dist-info/RECORD
